getLatestGitRelease/__init__.py
getLatestGitRelease-0.0.4.dist-info/LICENSE
getLatestGitRelease-0.0.4.dist-info/METADATA
getLatestGitRelease-0.0.4.dist-info/WHEEL
getLatestGitRelease-0.0.4.dist-info/top_level.txt
getLatestGitRelease-0.0.4.dist-info/RECORD
