Metadata-Version: 2.1
Name: getLatestGitRelease
Version: 0.0.4
Summary: Grabs the latest github release
Home-page: https://github.com/theflyingbadger/getLatestGitRelease
Author: Jonathan Mills
Author-email: jon@badger.shoes
License: UNKNOWN
Project-URL: Bug Tracker, https://github.com/theflyingbadger/getLatestGitRelease/issues
Project-URL: Source, https://github.com/theflyingbadger/getLatestGitRelease
Project-URL: Documentation, https://github.com/theflyingbadger/getLatestGitRelease/wiki
Platform: UNKNOWN
Classifier: Programming Language :: Python :: 3
Classifier: License :: OSI Approved :: MIT License
Classifier: Operating System :: OS Independent
Requires-Python: >=3.9
Requires-Dist: datasize
Requires-Dist: pywin32
Requires-Dist: ConfigFileHelper (>=0.0.2)
Requires-Dist: PyGithub
